gemini_imagen/__init__.py
gemini_imagen/_version.py
gemini_imagen/constants.py
gemini_imagen/gemini_image_wrapper.py
gemini_imagen/models.py
gemini_imagen/s3_utils.py
gemini_imagen/cli/__init__.py
gemini_imagen/cli/config.py
gemini_imagen/cli/job_merge.py
gemini_imagen/cli/langsmith_client.py
gemini_imagen/cli/langsmith_utils.py
gemini_imagen/cli/main.py
gemini_imagen/cli/templates.py
gemini_imagen/cli/utils.py
gemini_imagen/cli/variable_substitution.py
gemini_imagen/cli/commands/__init__.py
gemini_imagen/cli/commands/analyze.py
gemini_imagen/cli/commands/config_cmd.py
gemini_imagen/cli/commands/edit.py
gemini_imagen/cli/commands/generate.py
gemini_imagen/cli/commands/keys.py
gemini_imagen/cli/commands/langsmith.py
gemini_imagen/cli/commands/models.py
gemini_imagen/cli/commands/self_update.py
gemini_imagen/cli/commands/storage.py
gemini_imagen/cli/commands/template.py
gemini_imagen/cli/commands/version.py
gemini_imagen-0.6.6.dist-info/METADATA
gemini_imagen-0.6.6.dist-info/WHEEL
gemini_imagen-0.6.6.dist-info/entry_points.txt
gemini_imagen-0.6.6.dist-info/licenses/LICENSE
gemini_imagen-0.6.6.dist-info/RECORD
