Metadata-Version: 2.4
Name: gemini-imagen
Version: 0.6.6
Summary: A comprehensive Python wrapper for Google Gemini's image generation and analysis capabilities with S3 and LangSmith integration
Project-URL: Homepage, https://github.com/aviadr1/gemini-imagen
Project-URL: Documentation, https://github.com/aviadr1/gemini-imagen#readme
Project-URL: Repository, https://github.com/aviadr1/gemini-imagen
Project-URL: Issues, https://github.com/aviadr1/gemini-imagen/issues
Author-email: Aviad Rozenhek <aviadr1@gmail.com>
Maintainer-email: Aviad Rozenhek <aviadr1@gmail.com>
License: MIT
License-File: LICENSE
Keywords: ai,computer-vision,gemini,google,image-generation,imagen,langsmith,s3
Classifier: Development Status :: 4 - Beta
Classifier: Intended Audience :: Developers
Classifier: License :: OSI Approved :: MIT License
Classifier: Programming Language :: Python :: 3
Classifier: Programming Language :: Python :: 3.12
Classifier: Programming Language :: Python :: 3.13
Classifier: Topic :: Scientific/Engineering :: Artificial Intelligence
Classifier: Topic :: Software Development :: Libraries :: Python Modules
Requires-Python: >=3.12
Requires-Dist: aiofiles>=24.0.0
Requires-Dist: aiohttp>=3.9.0
Requires-Dist: click>=8.0.0
Requires-Dist: google-genai>=1.0.0
Requires-Dist: httpx>=0.27.0
Requires-Dist: langsmith>=0.1.0
Requires-Dist: pillow>=10.0.0
Requires-Dist: pydantic>=2.0.0
Requires-Dist: python-dotenv>=1.0.0
Requires-Dist: pyyaml>=6.0.0
Provides-Extra: dev
Requires-Dist: build>=1.0.0; extra == 'dev'
Requires-Dist: mypy>=1.11.0; extra == 'dev'
Requires-Dist: pre-commit>=3.5.0; extra == 'dev'
Requires-Dist: pytest-asyncio>=0.23.0; extra == 'dev'
Requires-Dist: pytest-cov>=5.0.0; extra == 'dev'
Requires-Dist: pytest-mock>=3.12.0; extra == 'dev'
Requires-Dist: pytest>=8.0.0; extra == 'dev'
Requires-Dist: ruff>=0.6.0; extra == 'dev'
Requires-Dist: twine>=5.0.0; extra == 'dev'
Requires-Dist: types-aiofiles>=24.0.0; extra == 'dev'
Requires-Dist: types-boto3>=1.34.0; extra == 'dev'
Requires-Dist: types-pillow>=10.0.0; extra == 'dev'
Requires-Dist: types-pyyaml>=6.0.0; extra == 'dev'
Provides-Extra: s3
Requires-Dist: aiobotocore>=2.11.0; extra == 's3'
Requires-Dist: boto3>=1.34.0; extra == 's3'
